aWaifu/__init__.py
aWaifu/__main__.py
aWaifu/species.py
aWaifu/utils.py
aWaifu-0.1.2.dist-info/LICENSE
aWaifu-0.1.2.dist-info/METADATA
aWaifu-0.1.2.dist-info/WHEEL
aWaifu-0.1.2.dist-info/entry_points.txt
aWaifu-0.1.2.dist-info/top_level.txt
aWaifu-0.1.2.dist-info/RECORD
