Metadata-Version: 2.1
Name: aWaifu
Version: 0.1.2
Summary: Mass waifu profile generator
Home-page: https://github.com/git-akihakune/aWaifu
Author: Aki Hakune
Author-email: akihakune@gmail.com
License: MIT
Platform: UNKNOWN
Classifier: License :: OSI Approved :: MIT License
Classifier: Programming Language :: Python :: 3
Requires-Dist: Pillow
Requires-Dist: Waifulabs
Requires-Dist: psutil
